OiRunner/BetterRunner.py
OiRunner/__init__.py
OiRunner/submit.py
OiRunner/util.py
tests/__init__.py
tests/test_basic.py
tests/test_func.py
tests/test_submit.py
tests/util.py
tests/data/a.in
tests/data/check.cpp
tests/data/check.exe
tests/data/check.out
tests/data/empty1.in
tests/data/empty2.in
tests/data/fail.cpp
tests/data/success.cpp
tests/data/check_data/1.ans
tests/data/check_data/1.in
tests/data/check_data/1.out
tests/data/check_data/2.ans
tests/data/check_data/2.in
tests/data/check_data/2.out
tests/data/check_data/3.ans
tests/data/check_data/3.in
tests/data/check_data/3.out
tests/data/check_data/large.ans
tests/data/check_data/large.in
tests/data/check_data/large.out
tests/data/test_freopen/test_freopen.cpp.bak
OiRunner-0.1.2.dist-info/LICENSE
OiRunner-0.1.2.dist-info/METADATA
OiRunner-0.1.2.dist-info/WHEEL
OiRunner-0.1.2.dist-info/entry_points.txt
OiRunner-0.1.2.dist-info/top_level.txt
OiRunner-0.1.2.dist-info/RECORD
