Metadata-Version: 2.1
Name: OiRunner
Version: 0.1.2
Summary: This package is designed to help oier compile the cpp file conveniently.
Home-page: https://github.com/ste1hi/OiRunner
Author: ste1
Author-email: ste1 <1874076121@qq.com>
License: MIT License
Classifier: Programming Language :: Python :: 3
Classifier: License :: OSI Approved :: MIT License
Classifier: Operating System :: POSIX :: Linux
Classifier: Operating System :: Microsoft :: Windows
Requires-Python: >=3.6
License-File: LICENSE
Requires-Dist: requests
